Metadata-Version: 2.1
Name: opendnn
Version: 0.0.1
Summary: opendnn
Home-page: https://github.com/quanhua92/opendnn
Author: Quan Hua
Author-email: support@opendnn.org
License: MIT
Platform: UNKNOWN
Classifier: License :: OSI Approved :: MIT License
Classifier: Programming Language :: Python :: 3
Classifier: Programming Language :: Python :: 3.5
Classifier: Programming Language :: Python :: 3.6
Classifier: Programming Language :: Python :: 3.7
Classifier: Programming Language :: Python :: 3.8
